{
    "EnableConnName": "MySQL",
    "DbConnStrings": {
        "MsSQLLocal": {
            "WorkDb": "server=(localdb)\\MSSQLLocalDB;database=workdb;Trusted_Connection=True;Connection Timeout=30;",
            "BackDb": "server=(localdb)\\MSSQLLocalDB;database=backdb;Trusted_Connection=True;Connection Timeout=30;"
        },
        "MsSQLExpress": {
            "WorkDb": "server=115.28.104.25\\SQLEXPRESS;database=workdb;Trusted_Connection=True;Connection Timeout=30;",
            "BackDb": "server=115.28.104.25\\SQLEXPRESS;database=backdb;Trusted_Connection=True;Connection Timeout=30;"
        },
        "MySQL": {
            "WorkDb": "server=custnet_mysql;user=root;password=123123;database=workdb;Connection Timeout=30;",
            "BackDb": "server=custnet_mysql;user=root;password=123123;database=backdb;Connection Timeout=30;"
        },
        "SQLite": {
            "WorkDb": "Data Source=workdb;Connection Timeout=30;",
            "BackDb": "Data Source=backdb;Connection Timeout=30;"
        }
    }
}